tests/__init__.py
tests/test_throw_catch.py
throw_catch/__init__.py
throw_catch/src.py
throw_catch-0.2.0.dist-info/LICENSE
throw_catch-0.2.0.dist-info/METADATA
throw_catch-0.2.0.dist-info/WHEEL
throw_catch-0.2.0.dist-info/top_level.txt
throw_catch-0.2.0.dist-info/RECORD
