Metadata-Version: 2.1
Name: throw-catch
Version: 0.2.0
Summary: RabbitMQ throw & catch messages
Home-page: https://github.com/Sobolev5/throw-catch/
Author: Sobolev Andrey
Author-email: email.asobolev@gmail.com
Classifier: Programming Language :: Python :: 3
Classifier: License :: OSI Approved :: MIT License
Classifier: Operating System :: OS Independent
Requires-Python: >=3.8
License-File: LICENSE
Requires-Dist: pika >=1.3
Requires-Dist: orjson >=3.8
